{"danceability": 0.671, "energy": 0.728, "key": 2, "loudness": -9.78, "mode": 0, "speechiness": 0.0403, "acousticness": 0.000372, "instrumentalness": 0.00391, "liveness": 0.385, "valence": 0.488, "tempo": 118.031, "type": "audio_features", "id": "0lLqS6XnoLYJJXHj57h4jz", "uri": "spotify:track:0lLqS6XnoLYJJXHj57h4jz", "track_href": "https://api.spotify.com/v1/tracks/0lLqS6XnoLYJJXHj57h4jz", "analysis_url": "https://api.spotify.com/v1/audio-analysis/0lLqS6XnoLYJJXHj57h4jz", "duration_ms": 472362, "time_signature": 4}