{"danceability": 0.659, "energy": 0.908, "key": 8, "loudness": -6.67, "mode": 0, "speechiness": 0.0367, "acousticness": 0.241, "instrumentalness": 0.00595, "liveness": 0.132, "valence": 0.741, "tempo": 159.008, "type": "audio_features", "id": "4u2dQmcZaFAu0fKXGmIf96", "uri": "spotify:track:4u2dQmcZaFAu0fKXGmIf96", "track_href": "https://api.spotify.com/v1/tracks/4u2dQmcZaFAu0fKXGmIf96", "analysis_url": "https://api.spotify.com/v1/audio-analysis/4u2dQmcZaFAu0fKXGmIf96", "duration_ms": 194120, "time_signature": 4}